darksky_async/__init__.py
darksky_async/alert.py
darksky_async/backoff.py
darksky_async/datablock.py
darksky_async/datapoint.py
darksky_async/exceptions.py
darksky_async/flag.py
darksky_async/forecast.py
darksky_async/http.py
darksky_async/sources.py
darksky_async/utils.py
darksky_async-1.0.2.dist-info/LICENCE
darksky_async-1.0.2.dist-info/METADATA
darksky_async-1.0.2.dist-info/WHEEL
darksky_async-1.0.2.dist-info/top_level.txt
darksky_async-1.0.2.dist-info/RECORD
