Metadata-Version: 2.1
Name: darksky-async
Version: 1.0.2
Summary: An async wrapper for DarkSky
Home-page: https://github.com/AggressivelyMeows/darksky_async
Author: Cerulean
Author-email: cerulean.connor@gmail.com
License: UNKNOWN
Platform: UNKNOWN
Classifier: Framework :: AsyncIO 
Classifier: Topic :: Scientific/Engineering :: Atmospheric Science
Classifier: Programming Language :: Python :: 3
Classifier: License :: OSI Approved :: MIT License
Classifier: Operating System :: OS Independent
